j5/__init__.py
j5/backends/__init__.py
j5/backends/backend.py
j5/backends/console/__init__.py
j5/backends/console/console.py
j5/backends/console/j5/__init__.py
j5/backends/console/j5/arduino.py
j5/backends/console/sb/__init__.py
j5/backends/console/sb/arduino.py
j5/backends/console/sr/__init__.py
j5/backends/console/sr/v4/__init__.py
j5/backends/console/sr/v4/motor_board.py
j5/backends/console/sr/v4/power_board.py
j5/backends/console/sr/v4/ruggeduino.py
j5/backends/console/sr/v4/servo_board.py
j5/backends/environment.py
j5/backends/hardware/__init__.py
j5/backends/hardware/env.py
j5/backends/hardware/j5/__init__.py
j5/backends/hardware/j5/arduino.py
j5/backends/hardware/j5/raw_usb.py
j5/backends/hardware/j5/serial.py
j5/backends/hardware/sb/__init__.py
j5/backends/hardware/sb/arduino.py
j5/backends/hardware/sr/__init__.py
j5/backends/hardware/sr/v4/__init__.py
j5/backends/hardware/sr/v4/legacy/__init__.py
j5/backends/hardware/sr/v4/legacy/power_board.py
j5/backends/hardware/sr/v4/motor_board.py
j5/backends/hardware/sr/v4/power_board.py
j5/backends/hardware/sr/v4/ruggeduino.py
j5/backends/hardware/sr/v4/serial/__init__.py
j5/backends/hardware/sr/v4/serial/power_board.py
j5/backends/hardware/sr/v4/serial/protocol.py
j5/backends/hardware/sr/v4/servo_board.py
j5/base_robot.py
j5/boards/__init__.py
j5/boards/arduino/__init__.py
j5/boards/arduino/uno.py
j5/boards/board.py
j5/boards/board_group.py
j5/boards/sb/__init__.py
j5/boards/sb/arduino.py
j5/boards/sr/__init__.py
j5/boards/sr/kch.py
j5/boards/sr/v4/__init__.py
j5/boards/sr/v4/motor_board.py
j5/boards/sr/v4/power_board.py
j5/boards/sr/v4/ruggeduino.py
j5/boards/sr/v4/servo_board.py
j5/components/__init__.py
j5/components/battery_sensor.py
j5/components/button.py
j5/components/component.py
j5/components/derived/__init__.py
j5/components/derived/ultrasound.py
j5/components/gpio_pin.py
j5/components/led.py
j5/components/motor.py
j5/components/piezo.py
j5/components/power_output.py
j5/components/pwm_led.py
j5-1.1.2.dist-info/LICENSE
j5-1.1.2.dist-info/WHEEL
j5-1.1.2.dist-info/METADATA
j5-1.1.2.dist-info/RECORD
