Metadata-Version: 2.1
Name: j5
Version: 1.1.2
Summary: j5 Robotics Framework
Home-page: https://j5.org.uk
License: MIT
Author: j5 contributors
Author-email: j5api@googlegroups.com
Requires-Python: >=3.7,<4.0
Classifier: Development Status :: 5 - Production/Stable
Classifier: License :: OSI Approved :: MIT License
Classifier: Operating System :: OS Independent
Classifier: Programming Language :: Python :: 3
Classifier: Programming Language :: Python :: 3.7
Classifier: Programming Language :: Python :: 3.8
Classifier: Programming Language :: Python :: 3.9
Classifier: Programming Language :: Python :: 3.10
Classifier: Programming Language :: Python :: 3.11
Classifier: Topic :: Education
Classifier: Topic :: Software Development :: Libraries :: Python Modules
Classifier: Typing :: Typed
Requires-Dist: pyserial (>=3.4,<4.0)
Requires-Dist: pyusb (>=1.0,<2.0)
Project-URL: Documentation, https://j5.org.uk
Project-URL: Repository, https://github.com/j5api/j5
